similaritycache/__init__.py
similaritycache/cache.py
similaritycache/node.py
similaritycache-0.1.1.dist-info/WHEEL
similaritycache-0.1.1.dist-info/entry_points.txt
similaritycache-0.1.1.dist-info/METADATA
similaritycache-0.1.1.dist-info/RECORD
