Metadata-Version: 2.3
Name: similaritycache
Version: 0.1.1
Summary: In-memory similarity cache
Author: Dênis Araújo da Silva
Author-email: Dênis Araújo da Silva <silvadenisaraujo@gmail.com>
Requires-Dist: numpy>=2.3.5
Requires-Dist: sentence-transformers>=5.2.0
Requires-Python: >=3.13
